odoo10_addon_web_favicon-10.0.1.0.0-py2.7-nspkg.pth
odoo10_addon_web_favicon-10.0.1.0.0.dist-info/top_level.txt
odoo10_addon_web_favicon-10.0.1.0.0.dist-info/WHEEL
odoo10_addon_web_favicon-10.0.1.0.0.dist-info/RECORD
odoo10_addon_web_favicon-10.0.1.0.0.dist-info/metadata.json
odoo10_addon_web_favicon-10.0.1.0.0.dist-info/DESCRIPTION.rst
odoo10_addon_web_favicon-10.0.1.0.0.dist-info/METADATA
odoo10_addon_web_favicon-10.0.1.0.0.dist-info/namespace_packages.txt
odoo/addons/web_favicon/__manifest__.py
odoo/addons/web_favicon/__init__.py
odoo/addons/web_favicon/README.rst
odoo/addons/web_favicon/models/__init__.py
odoo/addons/web_favicon/models/res_company.py
odoo/addons/web_favicon/views/res_company.xml
odoo/addons/web_favicon/views/templates.xml
odoo/addons/web_favicon/controllers/__init__.py
odoo/addons/web_favicon/controllers/web_favicon.py
odoo/addons/web_favicon/tests/__init__.py
odoo/addons/web_favicon/tests/test_web_favicon.py
odoo/addons/web_favicon/static/description/icon.png
odoo/addons/web_favicon/static/src/img/android-chrome-144x144.png
odoo/addons/web_favicon/static/src/img/apple-touch-icon-144x144.png
odoo/addons/web_favicon/static/src/img/android-chrome-48x48.png
odoo/addons/web_favicon/static/src/img/apple-touch-icon-72x72.png
odoo/addons/web_favicon/static/src/img/android-chrome-36x36.png
odoo/addons/web_favicon/static/src/img/mstile-310x150.png
odoo/addons/web_favicon/static/src/img/manifest.json
odoo/addons/web_favicon/static/src/img/android-chrome-72x72.png
odoo/addons/web_favicon/static/src/img/android-chrome-192x192.png
odoo/addons/web_favicon/static/src/img/apple-touch-icon-60x60.png
odoo/addons/web_favicon/static/src/img/master_original_favicon.svg
odoo/addons/web_favicon/static/src/img/android-chrome-96x96.png
odoo/addons/web_favicon/static/src/img/apple-touch-icon-76x76.png
odoo/addons/web_favicon/static/src/img/apple-touch-icon-152x152.png
odoo/addons/web_favicon/static/src/img/master_original_favicon.png
odoo/addons/web_favicon/static/src/img/apple-touch-icon-57x57.png
odoo/addons/web_favicon/static/src/img/apple-touch-icon-114x114.png
odoo/addons/web_favicon/static/src/img/apple-touch-icon-120x120.png
odoo/addons/web_favicon/static/src/img/apple-touch-icon-precomposed.png
odoo/addons/web_favicon/static/src/img/favicon-16x16.png
odoo/addons/web_favicon/static/src/img/browserconfig.xml
